hlm_texts/340-脂砚斋重批红楼梦.txt
hlm_texts/__init__.py
hlm_texts/david-hawks-the-story-of-the-stone.txt
hlm_texts/encoder.py
hlm_texts/fangfang-en.txt
hlm_texts/fangfang-zh.txt
hlm_texts/gen_tokens.py
hlm_texts/joly-hlm.txt
hlm_texts/load_text.py
hlm_texts/seg_text.py
hlm_texts/sent_tokenizer.py
hlm_texts/yang-hlm.txt
hlm_texts-0.1.8.dist-info/WHEEL
hlm_texts-0.1.8.dist-info/METADATA
hlm_texts-0.1.8.dist-info/RECORD
