Metadata-Version: 2.1
Name: hlm-texts
Version: 0.1.8
Summary: 
Home-page: https://github.com/ffreemt/hlm-texts
License: MIT
Author: freemt
Requires-Python: >=3.6.1,<4.0.0
Classifier: License :: OSI Approved :: MIT License
Classifier: Programming Language :: Python :: 3
Classifier: Programming Language :: Python :: 3.7
Classifier: Programming Language :: Python :: 3.8
Classifier: Programming Language :: Python :: 3.9
Requires-Dist: Morfessor (>=2.0.6,<3.0.0)
Requires-Dist: cchardet (>=2.1.7,<3.0.0)
Requires-Dist: halo (>=0.0.31,<0.0.32)
Requires-Dist: joblib (>=1.0.0,<2.0.0)
Requires-Dist: logzero (>=1.6.3,<2.0.0)
Requires-Dist: more-itertools (>=8.6.0,<9.0.0)
Requires-Dist: polyglot (>=16.7.4,<17.0.0)
Requires-Dist: sentence_splitter (>=1.4,<2.0)
Requires-Dist: tqdm (>=4.54.1,<5.0.0)
Project-URL: Repository, https://github.com/ffreemt/hlm-texts
